{
  "id": "8c30745d-7287-4140-b4d6-9d10430c8fa2",
  "question": "要人",
  "sourceAnswer": "important-person",
  "userAnswer": "",
  "activeAnswer": "important-person",
  "userExplanation": "",
  "userExplanationLong": "",
  "userMnemonic": "",
  "userCompounds": [],
  "readings": [
    "ようじん"
  ],
  "partsOfSpeech": "noun",
  "parsedTypeOfSpeech": "",
  "sourceMnemonic": "",
  "sourceReadingMnemonic": "",
  "audioB": "",
  "audioG": "",
  "audioTTS": "[sound:hypertts-746900fe0eab5cf1874fa03a72ba53b6d20dad0b649a31a83889e698.mp3]",
  "kanji": "",
  "forms": [
    "要人"
  ],
  "homophones": "",
  "sentenceCount": 1,
  "matchingRules": {
    "prefixIsNot": [],
    "suffixIsNot": [],
    "surfaceIsNot": [],
    "yieldToSurface": [],
    "requiredPrefix": []
  },
  "relatedVocab": {
    "ergativeTwin": "",
    "derivedFrom": "",
    "perfectSynonyms": [],
    "synonyms": [],
    "antonyms": [],
    "confusedWith": [],
    "seeAlso": []
  },
  "tags": [
    "-::vocab::has-no-studying-sentences",
    "source::jamdict"
  ]
}