{
  "sourceQuestion": "私のおばあちゃんは明治生まれです。",
  "userQuestion": "",
  "activeQuestion": "私のおばあちゃんは明治生まれです。",
  "sourceAnswer": "My grandmother was born in the Meiji era.",
  "userAnswer": "",
  "activeAnswer": "My grandmother was born in the Meiji era.",
  "sourceComments": "",
  "userComments": "",
  "reading": "",
  "externalId": "",
  "audio": "[sound:hypertts-d5d972fe61f6330a2e40fa77c5eb98fa229ee8fdbe5effd6657d2f1b.mp3]",
  "screenshot": "",
  "configuration": {
    "highlightedWords": [
      "明治"
    ],
    "incorrectMatches": [],
    "hiddenMatches": []
  },
  "parsingResult": {
    "sentence": "私のおばあちゃんは明治生まれです。",
    "parserVersion": "text_analysis_0.1",
    "parsedWords": [
      {
        "variant": "S",
        "startIndex": 0,
        "isDisplayed": true,
        "parsedForm": "私の",
        "vocabId": "4b154a26-4b7a-4eb5-bb96-eaafa39a3428"
      },
      {
        "variant": "S",
        "startIndex": 0,
        "isDisplayed": false,
        "parsedForm": "私",
        "vocabId": "b0feb775-fb1d-4097-b7bc-dbf87fae98a1"
      },
      {
        "variant": "S",
        "startIndex": 1,
        "isDisplayed": false,
        "parsedForm": "の",
        "vocabId": "33bf9bc1-0744-4973-8d45-5776bc54eac1"
      },
      {
        "variant": "S",
        "startIndex": 2,
        "isDisplayed": true,
        "parsedForm": "おばあちゃん",
        "vocabId": "8790479e-09a2-4cf3-9d3a-4f3d7e74aa79"
      },
      {
        "variant": "S",
        "startIndex": 2,
        "isDisplayed": false,
        "parsedForm": "お",
        "vocabId": "25afbecf-5751-4f2b-a02a-ab0a5bf739d8"
      },
      {
        "variant": "S",
        "startIndex": 3,
        "isDisplayed": false,
        "parsedForm": "ばあちゃん",
        "vocabId": "f121523e-3d01-47b0-8391-ce40163df01b"
      },
      {
        "variant": "S",
        "startIndex": 8,
        "isDisplayed": true,
        "parsedForm": "は",
        "vocabId": "825f4f56-9e9b-4eb9-92e2-099dc6d0c677"
      },
      {
        "variant": "S",
        "startIndex": 9,
        "isDisplayed": true,
        "parsedForm": "明治",
        "vocabId": "07f57bea-5435-4e25-bb85-d05b9da3ef9a"
      },
      {
        "variant": "S",
        "startIndex": 11,
        "isDisplayed": true,
        "parsedForm": "生まれ",
        "vocabId": "6c9d2a3f-5d01-4915-99e2-164201dc3f7f"
      },
      {
        "variant": "S",
        "startIndex": 14,
        "isDisplayed": true,
        "parsedForm": "です",
        "vocabId": "01fd4128-aa4d-4a4d-a529-1e7a3b5d4a0a"
      }
    ]
  },
  "janomeTokens": "名詞,代名詞,一般,*​私​私​*​*​ワタシ​ワタシ​SYS_DICT\n助詞,連体化,*,*​の​の​*​*​ノ​ノ​SYS_DICT\n接頭詞,名詞接続,*,*​お​お​*​*​オ​オ​SYS_DICT\n名詞,一般,*,*​ばあちゃん​ばあちゃん​*​*​バアチャン​バーチャン​SYS_DICT\n助詞,係助詞,*,*​は​は​*​*​ハ​ワ​SYS_DICT\n名詞,固有名詞,一般,*​明治​明治​*​*​メイジ​メイジ​SYS_DICT\n名詞,一般,*,*​生まれ​生まれ​*​*​ウマレ​ウマレ​SYS_DICT\n助動詞,*,*,*​です​です​特殊・デス​基本形​デス​デス​SYS_DICT\n記号,句点,*,*​。​。​*​*​。​。​SYS_DICT",
  "id": "921031ba-8cd0-48ea-884e-01cfefd77070",
  "tags": [
    "_tts_audio",
    "-::priority::low::120_tts",
    "-::sentence::difficulty::4",
    "source::wani",
    "source::wani::current"
  ]
}