{
  "id": "b138884e-155e-4787-be05-1ea0e24529b1",
  "sourceQuestion": "夏目",
  "userQuestion": "",
  "activeQuestion": "夏目",
  "sourceAnswer": "Natsume!",
  "userAnswer": "",
  "activeAnswer": "Natsume!",
  "sourceComments": "",
  "userComments": "",
  "reading": "夏目[なつめ]",
  "externalId": "ny3-nodup_01_0.16.06.160-0.16.06.880",
  "audio": "[sound:ny3-nodup_01_0.16.06.160-0.16.06.880.mp3]",
  "screenshot": "<img src=\"ny3-nodup_01_0.16.06.560.jpg\">",
  "configuration": {
    "highlightedWords": [],
    "incorrectMatches": [],
    "hiddenMatches": []
  },
  "parsingResult": {
    "sentence": "夏目",
    "parserVersion": "text_analysis_0.1",
    "parsedWords": [
      {
        "variant": "S",
        "startIndex": 0,
        "isDisplayed": true,
        "parsedForm": "夏目",
        "vocabId": null
      }
    ]
  },
  "janomeTokens": "",
  "tags": [
    "-::priority::high::011_Natsume_03",
    "-::sentence::difficulty::1",
    "source::anime::natsume::s3::01"
  ]
}