{
  "question": "持ち出す",
  "sourceAnswer": "to{} take-out/carry-out/bring-out-from-where-it-belongs | mention-something/broach-a-topic/bring-up-(a-subject)/raise-(an-issue)/mention",
  "userAnswer": "",
  "activeAnswer": "to{} take-out/carry-out/bring-out-from-where-it-belongs | mention-something/broach-a-topic/bring-up-(a-subject)/raise-(an-issue)/mention",
  "userExplanation": "",
  "userExplanationLong": "",
  "userMnemonic": "",
  "userCompounds": [],
  "readings": [
    "もちだす"
  ],
  "partsOfSpeech": "godan verb, transitive",
  "sourceMnemonic": "",
  "sourceReadingMnemonic": "",
  "audioB": "",
  "audioG": "",
  "audioTTS": "[sound:hypertts-e9febe6996df93542dd179042674dfb372ee255cee72c1434fff8fec.mp3]",
  "forms": [
    "持ち出す"
  ],
  "sentenceCount": 4,
  "technicalNotes": "",
  "references": "",
  "matchingRules": {
    "prefixIsNot": [],
    "suffixIsNot": [],
    "surfaceIsNot": [],
    "yieldToSurface": [],
    "requiredPrefix": []
  },
  "relatedVocab": {
    "ergativeTwin": "",
    "derivedFrom": "",
    "perfectSynonyms": [],
    "synonyms": [],
    "antonyms": [],
    "confusedWith": [],
    "seeAlso": []
  },
  "id": "46121661-2a09-449d-a521-63582acf878e",
  "tags": [
    "-::vocab::has-no-studying-sentences",
    "source::jamdict"
  ]
}