{
  "sourceQuestion": "光？",
  "userQuestion": "",
  "activeQuestion": "光？",
  "sourceAnswer": "Light?",
  "userAnswer": "",
  "activeAnswer": "Light?",
  "sourceComments": "",
  "userComments": "",
  "reading": "光[ひかり]？",
  "externalId": "ny6-nodup_05_0.03.37.500-0.03.38.270",
  "audio": "[sound:ny6-nodup_05_0.03.37.500-0.03.38.270.mp3]",
  "screenshot": "<img src=\"ny6-nodup_05_0.03.37.885.jpg\">",
  "configuration": {
    "highlightedWords": [],
    "incorrectMatches": [],
    "hiddenMatches": []
  },
  "parsingResult": {
    "sentence": "光？",
    "parserVersion": "text_analysis_0.1",
    "parsedWords": [
      {
        "variant": "S",
        "startIndex": 0,
        "isDisplayed": true,
        "parsedForm": "光",
        "vocabId": "9252e71f-6868-407f-aedf-77056684b426"
      }
    ]
  },
  "janomeTokens": "名詞,一般,*,*​光​光​*​*​ヒカリ​ヒカリ​SYS_DICT\n記号,一般,*,*​？​？​*​*​？​？​SYS_DICT",
  "id": "0d483926-0043-4034-b5d8-ad99c3a177a7",
  "tags": [
    "-::priority::high::011_Natsume_06",
    "-::sentence::difficulty::1",
    "source::anime::natsume::s6::05"
  ]
}