{
  "sourceQuestion": "生命保険、入ってる？",
  "userQuestion": "",
  "activeQuestion": "生命保険、入ってる？",
  "sourceAnswer": "Do you have life insurance?",
  "userAnswer": "",
  "activeAnswer": "Do you have life insurance?",
  "sourceComments": "",
  "userComments": "",
  "reading": "",
  "externalId": "",
  "audio": "[sound:hypertts-18243862791de73b16e5d220eb52edbc155c8106b5c48fdb1f6ea0e5.mp3]",
  "screenshot": "",
  "configuration": {
    "highlightedWords": [
      "保険"
    ],
    "incorrectMatches": [],
    "hiddenMatches": []
  },
  "parsingResult": {
    "sentence": "生命保険、入ってる？",
    "parserVersion": "text_analysis_0.1",
    "parsedWords": [
      {
        "variant": "S",
        "startIndex": 0,
        "isDisplayed": true,
        "parsedForm": "生命保険",
        "vocabId": "c13dcf60-5c78-4cb8-bf6f-041bf5c5c062"
      },
      {
        "variant": "S",
        "startIndex": 0,
        "isDisplayed": false,
        "parsedForm": "生命",
        "vocabId": "56d3d584-a073-4b8b-983a-50b0e816fcd3"
      },
      {
        "variant": "S",
        "startIndex": 2,
        "isDisplayed": false,
        "parsedForm": "保険",
        "vocabId": "1c3bb35f-8801-4e31-94c3-2b6b22d55286"
      },
      {
        "variant": "S",
        "startIndex": 5,
        "isDisplayed": true,
        "parsedForm": "入ってる",
        "vocabId": "77707cfb-5cdf-4b39-9639-fec120251132"
      },
      {
        "variant": "B",
        "startIndex": 5,
        "isDisplayed": false,
        "parsedForm": "入る",
        "vocabId": "550a7bf3-49b1-4c1e-bf28-df957562d75d"
      },
      {
        "variant": "S",
        "startIndex": 7,
        "isDisplayed": false,
        "parsedForm": "てる",
        "vocabId": "4c8d7119-0464-426c-88b7-ee97c1554eb5"
      }
    ]
  },
  "janomeTokens": "名詞,一般,*,*​生命​生命​*​*​セイメイ​セイメイ​SYS_DICT\n名詞,一般,*,*​保険​保険​*​*​ホケン​ホケン​SYS_DICT\n記号,読点,*,*​、​、​*​*​、​、​SYS_DICT\n動詞,自立,*,*​入る​入っ​五段・ラ行​連用タ接続​ハイッ​ハイッ​SYS_DICT\n動詞,非自立,*,*​てる​てる​一段​基本形​テル​テル​SYS_DICT\n記号,一般,*,*​？​？​*​*​？​？​SYS_DICT",
  "id": "2a9a9934-d028-4bf4-b46a-661260a74363",
  "tags": [
    "_tts_audio",
    "-::priority::low::120_tts",
    "-::sentence::difficulty::4",
    "source::wani",
    "source::wani::current"
  ]
}