{
  "id": "00576cc7-e09a-43ed-b28d-2e69bdb75535",
  "sourceQuestion": "薬屋さんで薬をもらってきました。",
  "userQuestion": "",
  "activeQuestion": "薬屋さんで薬をもらってきました。",
  "sourceAnswer": "I got the medicine at the pharmacy.",
  "userAnswer": "",
  "activeAnswer": "I got the medicine at the pharmacy.",
  "sourceComments": "",
  "userComments": "",
  "reading": "",
  "externalId": "",
  "audio": "[sound:hypertts-8098b4585f1b2690d0765d1b4281a7e17399e4c14f25dcb561f6c349.mp3]",
  "screenshot": "",
  "configuration": {
    "highlightedWords": [
      "薬"
    ],
    "incorrectMatches": [],
    "hiddenMatches": []
  },
  "parsingResult": {
    "sentence": "薬屋さんで薬をもらってきました。",
    "parserVersion": "text_analysis_0.1",
    "parsedWords": [
      {
        "variant": "S",
        "startIndex": 0,
        "isDisplayed": true,
        "parsedForm": "薬屋",
        "vocabId": null
      },
      {
        "variant": "S",
        "startIndex": 0,
        "isDisplayed": false,
        "parsedForm": "薬",
        "vocabId": null
      },
      {
        "variant": "S",
        "startIndex": 1,
        "isDisplayed": false,
        "parsedForm": "屋",
        "vocabId": null
      },
      {
        "variant": "S",
        "startIndex": 2,
        "isDisplayed": true,
        "parsedForm": "さん",
        "vocabId": null
      },
      {
        "variant": "S",
        "startIndex": 4,
        "isDisplayed": true,
        "parsedForm": "で",
        "vocabId": null
      },
      {
        "variant": "S",
        "startIndex": 5,
        "isDisplayed": true,
        "parsedForm": "薬",
        "vocabId": null
      },
      {
        "variant": "S",
        "startIndex": 6,
        "isDisplayed": true,
        "parsedForm": "を",
        "vocabId": null
      },
      {
        "variant": "B",
        "startIndex": 7,
        "isDisplayed": true,
        "parsedForm": "もらう",
        "vocabId": null
      },
      {
        "variant": "S",
        "startIndex": 10,
        "isDisplayed": true,
        "parsedForm": "てきました",
        "vocabId": null
      },
      {
        "variant": "B",
        "startIndex": 10,
        "isDisplayed": false,
        "parsedForm": "てきます",
        "vocabId": null
      },
      {
        "variant": "B",
        "startIndex": 10,
        "isDisplayed": false,
        "parsedForm": "てくる",
        "vocabId": null
      },
      {
        "variant": "S",
        "startIndex": 10,
        "isDisplayed": false,
        "parsedForm": "て",
        "vocabId": null
      },
      {
        "variant": "B",
        "startIndex": 11,
        "isDisplayed": false,
        "parsedForm": "くる",
        "vocabId": null
      },
      {
        "variant": "S",
        "startIndex": 12,
        "isDisplayed": false,
        "parsedForm": "ました",
        "vocabId": null
      },
      {
        "variant": "B",
        "startIndex": 12,
        "isDisplayed": false,
        "parsedForm": "ます",
        "vocabId": null
      },
      {
        "variant": "S",
        "startIndex": 14,
        "isDisplayed": false,
        "parsedForm": "た",
        "vocabId": null
      }
    ]
  },
  "janomeTokens": "",
  "tags": [
    "_tts_audio",
    "-::priority::low::120_tts",
    "-::sentence::difficulty::4",
    "source::wani",
    "source::wani::current"
  ]
}