{
  "id": "76d7c7f3-fae4-480b-bc60-9367709e23ee",
  "sourceQuestion": "どうして犯人が遺体の唇を舐めたのかは不明です。",
  "userQuestion": "",
  "activeQuestion": "どうして犯人が遺体の唇を舐めたのかは不明です。",
  "sourceAnswer": "We have no idea why the murderer licked the corpse’s lips.",
  "userAnswer": "",
  "activeAnswer": "We have no idea why the murderer licked the corpse’s lips.",
  "sourceComments": "",
  "userComments": "",
  "reading": "",
  "externalId": "",
  "audio": "[sound:hypertts-bbbc70a7b48e69e79ce254acf1555385098ef7166b66697466c6cd8f.mp3]",
  "screenshot": "",
  "configuration": {
    "highlightedWords": [
      "遺体"
    ],
    "incorrectMatches": [],
    "hiddenMatches": []
  },
  "parsingResult": {
    "sentence": "どうして犯人が遺体の唇を舐めたのかは不明です。",
    "parserVersion": "text_analysis_0.1",
    "parsedWords": [
      {
        "variant": "S",
        "startIndex": 0,
        "isDisplayed": true,
        "parsedForm": "どうして",
        "vocabId": null
      },
      {
        "variant": "S",
        "startIndex": 4,
        "isDisplayed": true,
        "parsedForm": "犯人",
        "vocabId": null
      },
      {
        "variant": "S",
        "startIndex": 6,
        "isDisplayed": true,
        "parsedForm": "が",
        "vocabId": null
      },
      {
        "variant": "S",
        "startIndex": 7,
        "isDisplayed": true,
        "parsedForm": "遺体",
        "vocabId": null
      },
      {
        "variant": "S",
        "startIndex": 9,
        "isDisplayed": true,
        "parsedForm": "の",
        "vocabId": null
      },
      {
        "variant": "S",
        "startIndex": 10,
        "isDisplayed": true,
        "parsedForm": "唇",
        "vocabId": null
      },
      {
        "variant": "S",
        "startIndex": 11,
        "isDisplayed": true,
        "parsedForm": "を",
        "vocabId": null
      },
      {
        "variant": "B",
        "startIndex": 12,
        "isDisplayed": true,
        "parsedForm": "舐める",
        "vocabId": null
      },
      {
        "variant": "S",
        "startIndex": 14,
        "isDisplayed": true,
        "parsedForm": "た",
        "vocabId": null
      },
      {
        "variant": "S",
        "startIndex": 15,
        "isDisplayed": true,
        "parsedForm": "の",
        "vocabId": null
      },
      {
        "variant": "S",
        "startIndex": 16,
        "isDisplayed": true,
        "parsedForm": "か",
        "vocabId": null
      },
      {
        "variant": "S",
        "startIndex": 17,
        "isDisplayed": true,
        "parsedForm": "は",
        "vocabId": null
      },
      {
        "variant": "S",
        "startIndex": 18,
        "isDisplayed": true,
        "parsedForm": "不明",
        "vocabId": null
      },
      {
        "variant": "S",
        "startIndex": 20,
        "isDisplayed": true,
        "parsedForm": "です",
        "vocabId": null
      }
    ]
  },
  "janomeTokens": "",
  "tags": [
    "_tts_audio",
    "-::priority::low::120_tts",
    "-::sentence::difficulty::5",
    "source::wani",
    "source::wani::current"
  ]
}