{
  "question": "月日が経つ",
  "sourceAnswer": "time-passes/the-days-and-months-go-by/the-months-roll-on",
  "userAnswer": "",
  "activeAnswer": "time-passes/the-days-and-months-go-by/the-months-roll-on",
  "userExplanation": "",
  "userExplanationLong": "",
  "userMnemonic": "",
  "userCompounds": [],
  "readings": [
    "つきひがたつ"
  ],
  "partsOfSpeech": "expression, godan verb",
  "sourceMnemonic": "",
  "sourceReadingMnemonic": "",
  "audioB": "",
  "audioG": "",
  "audioTTS": "[sound:hypertts-f415174195e9439a21f1272d6d767ef6377f5ab1c4ab27d0bd97578c.mp3]",
  "forms": [
    "月日が経つ"
  ],
  "sentenceCount": 1,
  "matchingRules": {
    "prefixIsNot": [],
    "suffixIsNot": [],
    "surfaceIsNot": [],
    "yieldToSurface": [],
    "requiredPrefix": []
  },
  "relatedVocab": {
    "ergativeTwin": "",
    "derivedFrom": "",
    "perfectSynonyms": [],
    "synonyms": [],
    "antonyms": [],
    "confusedWith": [],
    "seeAlso": []
  },
  "id": "f000f186-abeb-4ac6-98b5-b8266f987e80",
  "tags": [
    "-::vocab::has-no-studying-sentences",
    "source::jamdict"
  ]
}