{
  "id": "fc7e8662-189a-4a91-9efe-7bf5d48a3365",
  "sourceQuestion": "相手は強くなっていく",
  "userQuestion": "",
  "activeQuestion": "相手は強くなっていく",
  "sourceAnswer": "[You] opponent continuously becomes stronger.",
  "userAnswer": "Your opponent is getting stronger.",
  "activeAnswer": "Your opponent is getting stronger.",
  "sourceComments": "",
  "userComments": "",
  "reading": "あいて は つよく なって いく",
  "externalId": "1600431430000",
  "audio": "[sound:1600431430000.mp3]",
  "screenshot": "<img src=\"1600431430000.jpg\">",
  "configuration": {
    "highlightedWords": [
      "ていく"
    ],
    "incorrectMatches": [],
    "hiddenMatches": []
  },
  "parsingResult": {
    "sentence": "相手は強くなっていく",
    "parserVersion": "text_analysis_0.1",
    "parsedWords": [
      {
        "variant": "S",
        "startIndex": 0,
        "isDisplayed": true,
        "parsedForm": "相手",
        "vocabId": null
      },
      {
        "variant": "S",
        "startIndex": 2,
        "isDisplayed": true,
        "parsedForm": "は",
        "vocabId": null
      },
      {
        "variant": "B",
        "startIndex": 3,
        "isDisplayed": true,
        "parsedForm": "強い",
        "vocabId": null
      },
      {
        "variant": "S",
        "startIndex": 5,
        "isDisplayed": true,
        "parsedForm": "なっていく",
        "vocabId": null
      },
      {
        "variant": "B",
        "startIndex": 5,
        "isDisplayed": false,
        "parsedForm": "なっていく",
        "vocabId": null
      },
      {
        "variant": "B",
        "startIndex": 4,
        "isDisplayed": false,
        "parsedForm": "くなる",
        "vocabId": null
      },
      {
        "variant": "S",
        "startIndex": 7,
        "isDisplayed": false,
        "parsedForm": "ていく",
        "vocabId": null
      },
      {
        "variant": "B",
        "startIndex": 7,
        "isDisplayed": false,
        "parsedForm": "ていく",
        "vocabId": null
      },
      {
        "variant": "S",
        "startIndex": 7,
        "isDisplayed": false,
        "parsedForm": "て",
        "vocabId": null
      },
      {
        "variant": "S",
        "startIndex": 8,
        "isDisplayed": false,
        "parsedForm": "いく",
        "vocabId": null
      },
      {
        "variant": "B",
        "startIndex": 8,
        "isDisplayed": false,
        "parsedForm": "いく",
        "vocabId": null
      },
      {
        "variant": "B",
        "startIndex": 9,
        "isDisplayed": true,
        "parsedForm": "う",
        "vocabId": null
      }
    ]
  },
  "janomeTokens": "",
  "tags": [
    "-::priority::medium::15-jlab-beginner",
    "-::sentence::difficulty::3",
    "legacy_scheduling",
    "source::jlab::beginner"
  ]
}