{
  "id": "f894a561-8bf3-41a0-841c-06db11851c71",
  "sourceQuestion": "今超貧乏でさ〜。砂糖も切らしてるんだけど、それすら新しいの買えないんだわ。",
  "userQuestion": "",
  "activeQuestion": "今超貧乏でさ〜。砂糖も切らしてるんだけど、それすら新しいの買えないんだわ。",
  "sourceAnswer": "I’m super broke right now. I’ve run out of sugar and I can’t even buy more.",
  "userAnswer": "",
  "activeAnswer": "I’m super broke right now. I’ve run out of sugar and I can’t even buy more.",
  "sourceComments": "",
  "userComments": "",
  "reading": "",
  "externalId": "",
  "audio": "[sound:hypertts-2e884f36c1569be492fbc87d7b2163a9e3b2b38ec8cb187baac70f6b.mp3]",
  "screenshot": "",
  "configuration": {
    "highlightedWords": [
      "超〜"
    ],
    "incorrectMatches": [],
    "hiddenMatches": []
  },
  "parsingResult": {
    "sentence": "今超貧乏でさ〜。砂糖も切らしてるんだけど、それすら新しいの買えないんだわ。",
    "parserVersion": "text_analysis_0.1",
    "parsedWords": [
      {
        "variant": "S",
        "startIndex": 0,
        "isDisplayed": true,
        "parsedForm": "今",
        "vocabId": "f41ddbeb-67a3-4644-a57a-bf3327a266db"
      },
      {
        "variant": "S",
        "startIndex": 1,
        "isDisplayed": true,
        "parsedForm": "超",
        "vocabId": "3877c4a9-353b-42c9-816b-ff494ba8f2bf"
      },
      {
        "variant": "S",
        "startIndex": 2,
        "isDisplayed": true,
        "parsedForm": "貧乏",
        "vocabId": "3c40a94f-199f-44a6-b33c-cfad615e6c48"
      },
      {
        "variant": "S",
        "startIndex": 4,
        "isDisplayed": true,
        "parsedForm": "でさ",
        "vocabId": "592202fe-33eb-435f-a26b-949014ced872"
      },
      {
        "variant": "S",
        "startIndex": 4,
        "isDisplayed": false,
        "parsedForm": "で",
        "vocabId": "67a62904-bc8a-4b97-8ea5-69364da19acd"
      },
      {
        "variant": "S",
        "startIndex": 5,
        "isDisplayed": false,
        "parsedForm": "さ",
        "vocabId": "10abfe8f-b536-47d9-b129-bfa04813dfae"
      },
      {
        "variant": "S",
        "startIndex": 6,
        "isDisplayed": true,
        "parsedForm": "〜",
        "vocabId": "67087f64-b677-467f-a421-65d5db7e944e"
      },
      {
        "variant": "S",
        "startIndex": 8,
        "isDisplayed": true,
        "parsedForm": "砂糖",
        "vocabId": "26e36676-6c04-4d53-b3d2-1b6affdf42cc"
      },
      {
        "variant": "S",
        "startIndex": 10,
        "isDisplayed": true,
        "parsedForm": "も",
        "vocabId": "156f9454-37f8-4b10-a6e7-3abe39897c8b"
      },
      {
        "variant": "B",
        "startIndex": 11,
        "isDisplayed": true,
        "parsedForm": "切らす",
        "vocabId": "feff5ef6-6ceb-497a-a8a6-0f5f057ab36f"
      },
      {
        "variant": "S",
        "startIndex": 14,
        "isDisplayed": true,
        "parsedForm": "てる",
        "vocabId": "4c8d7119-0464-426c-88b7-ee97c1554eb5"
      },
      {
        "variant": "S",
        "startIndex": 16,
        "isDisplayed": false,
        "parsedForm": "んだ",
        "vocabId": "83865919-ae21-4d86-b814-f700651c09ac"
      },
      {
        "variant": "S",
        "startIndex": 16,
        "isDisplayed": true,
        "parsedForm": "ん",
        "vocabId": "cc6433c2-80a1-498d-8f0d-9da2a46c2885"
      },
      {
        "variant": "S",
        "startIndex": 17,
        "isDisplayed": true,
        "parsedForm": "だけど",
        "vocabId": "efb594c0-b6dd-46a0-9a3b-265e53b1cfdc"
      },
      {
        "variant": "S",
        "startIndex": 17,
        "isDisplayed": false,
        "parsedForm": "だ",
        "vocabId": "32d275aa-5811-482d-b2f3-7e6d2080ac53"
      },
      {
        "variant": "S",
        "startIndex": 18,
        "isDisplayed": false,
        "parsedForm": "けど",
        "vocabId": "fd306f09-1bc3-4f74-ab92-95e10af2db51"
      },
      {
        "variant": "S",
        "startIndex": 21,
        "isDisplayed": true,
        "parsedForm": "それすら",
        "vocabId": "8d7cdc66-f7f9-4100-9cf9-8a8af3b20dd4"
      },
      {
        "variant": "S",
        "startIndex": 21,
        "isDisplayed": false,
        "parsedForm": "それ",
        "vocabId": "649623f9-ee80-4187-b7b3-955e4738b82d"
      },
      {
        "variant": "S",
        "startIndex": 23,
        "isDisplayed": false,
        "parsedForm": "すら",
        "vocabId": "b322cac0-c49d-4405-a027-1fa8a3507c17"
      },
      {
        "variant": "S",
        "startIndex": 25,
        "isDisplayed": true,
        "parsedForm": "新しい",
        "vocabId": "69af8c23-df5b-4244-b71e-31ae61f9aa01"
      },
      {
        "variant": "S",
        "startIndex": 28,
        "isDisplayed": true,
        "parsedForm": "の",
        "vocabId": "33bf9bc1-0744-4973-8d45-5776bc54eac1"
      },
      {
        "variant": "B",
        "startIndex": 29,
        "isDisplayed": true,
        "parsedForm": "買う",
        "vocabId": null
      },
      {
        "variant": "S",
        "startIndex": 30,
        "isDisplayed": true,
        "parsedForm": "えない",
        "vocabId": "efce9e5a-170d-4164-9308-3b7eeec0d090"
      },
      {
        "variant": "B",
        "startIndex": 30,
        "isDisplayed": false,
        "parsedForm": "える",
        "vocabId": "915ce682-39f5-4e53-92fe-c786863a0e86"
      },
      {
        "variant": "S",
        "startIndex": 31,
        "isDisplayed": false,
        "parsedForm": "ない",
        "vocabId": "1d4932a0-8cac-4af7-8a41-3b8a0d69fe9f"
      },
      {
        "variant": "S",
        "startIndex": 33,
        "isDisplayed": true,
        "parsedForm": "んだ",
        "vocabId": "83865919-ae21-4d86-b814-f700651c09ac"
      },
      {
        "variant": "S",
        "startIndex": 33,
        "isDisplayed": false,
        "parsedForm": "ん",
        "vocabId": "cc6433c2-80a1-498d-8f0d-9da2a46c2885"
      },
      {
        "variant": "S",
        "startIndex": 34,
        "isDisplayed": false,
        "parsedForm": "だ",
        "vocabId": "32d275aa-5811-482d-b2f3-7e6d2080ac53"
      },
      {
        "variant": "S",
        "startIndex": 35,
        "isDisplayed": true,
        "parsedForm": "わ",
        "vocabId": "b3ff5194-b2ec-415c-9995-a96012a507c0"
      }
    ]
  },
  "janomeTokens": "接頭詞,名詞接続,*,*​今​今​*​*​コン​コン​SYS_DICT\n接頭詞,名詞接続,*,*​超​超​*​*​チョウ​チョー​SYS_DICT\n名詞,形容動詞語幹,*,*​貧乏​貧乏​*​*​ビンボウ​ビンボー​SYS_DICT\n助動詞,*,*,*​だ​で​特殊・ダ​連用形​デ​デ​SYS_DICT\n助詞,終助詞,*,*​さ​さ​*​*​サ​サ​SYS_DICT\n記号,一般,*,*​〜​〜​*​*​〜​〜​SYS_DICT\n記号,句点,*,*​。​。​*​*​。​。​SYS_DICT\n名詞,一般,*,*​砂糖​砂糖​*​*​サトウ​サトー​SYS_DICT\n助詞,係助詞,*,*​も​も​*​*​モ​モ​SYS_DICT\n動詞,自立,*,*​切らす​切らし​五段・サ行​連用形​キラシ​キラシ​SYS_DICT\n動詞,非自立,*,*​てる​てる​一段​基本形​テル​テル​SYS_DICT\n名詞,非自立,一般,*​ん​ん​*​*​ン​ン​SYS_DICT\n助動詞,*,*,*​だ​だ​特殊・ダ​基本形​ダ​ダ​SYS_DICT\n助詞,接続助詞,*,*​けど​けど​*​*​ケド​ケド​SYS_DICT\n記号,読点,*,*​、​、​*​*​、​、​SYS_DICT\n名詞,代名詞,一般,*​それ​それ​*​*​ソレ​ソレ​SYS_DICT\n助詞,係助詞,*,*​すら​すら​*​*​スラ​スラ​SYS_DICT\n形容詞,自立,*,*​新しい​新しい​形容詞・イ段​基本形​アタラシイ​アタラシイ​SYS_DICT\n名詞,非自立,一般,*​の​の​*​*​ノ​ノ​SYS_DICT\n動詞,自立,*,*​買える​買え​一段​未然形​カエ​カエ​SYS_DICT\n助動詞,*,*,*​ない​ない​特殊・ナイ​基本形​ナイ​ナイ​SYS_DICT\n名詞,非自立,一般,*​ん​ん​*​*​ン​ン​SYS_DICT\n助動詞,*,*,*​だ​だ​特殊・ダ​基本形​ダ​ダ​SYS_DICT\n助詞,終助詞,*,*​わ​わ​*​*​ワ​ワ​SYS_DICT\n記号,句点,*,*​。​。​*​*​。​。​SYS_DICT",
  "tags": [
    "_tts_audio",
    "-::priority::low::120_tts",
    "-::sentence::difficulty::6",
    "source::wani",
    "source::wani::current"
  ]
}