{
  "id": "efc5cb83-9197-4735-b776-4c72a79f3234",
  "sourceQuestion": "速度が落ちる所\u3000そして破壊されると復旧が難しい所",
  "userQuestion": "",
  "activeQuestion": "速度が落ちる所\u3000そして破壊されると復旧が難しい所",
  "sourceAnswer": "Somewhere the train needs to slow down, and somewhere it'll be hard to make repairs.",
  "userAnswer": "",
  "activeAnswer": "Somewhere the train needs to slow down, and somewhere it'll be hard to make repairs.",
  "sourceComments": "",
  "userComments": "",
  "reading": "速度[そくど]が 落[お]ちる 所[ところ]\u3000そして 破壊[はかい]されると 復旧[ふっきゅう]が 難[むずか]しい 所[ところ]",
  "externalId": "A_VioletEvergarden_S01_E12_2953",
  "audio": "[sound:A_VioletEvergarden_12_0.13.38.900-0.13.44.240.mp3]",
  "screenshot": "<img src=\"A_VioletEvergarden_12_0.13.41.570.jpg\">",
  "configuration": {
    "highlightedWords": [],
    "incorrectMatches": [],
    "hiddenMatches": []
  },
  "parsingResult": {
    "sentence": "速度が落ちる所\u3000そして破壊されると復旧が難しい所",
    "parserVersion": "text_analysis_0.1",
    "parsedWords": [
      {
        "variant": "S",
        "startIndex": 0,
        "isDisplayed": true,
        "parsedForm": "速度",
        "vocabId": "8cb33607-7f0b-48e1-8329-dc204df0e952"
      },
      {
        "variant": "S",
        "startIndex": 2,
        "isDisplayed": true,
        "parsedForm": "が",
        "vocabId": "2abe98f2-ebd9-4aae-9562-451647960317"
      },
      {
        "variant": "S",
        "startIndex": 3,
        "isDisplayed": true,
        "parsedForm": "落ちる",
        "vocabId": "01cf8b65-2def-42df-8c9f-f68959bf539e"
      },
      {
        "variant": "B",
        "startIndex": 3,
        "isDisplayed": false,
        "parsedForm": "落ちる",
        "vocabId": "01cf8b65-2def-42df-8c9f-f68959bf539e"
      },
      {
        "variant": "S",
        "startIndex": 5,
        "isDisplayed": true,
        "parsedForm": "う",
        "vocabId": "dcca0586-d8a4-4281-9f5f-a50f58a75fb2"
      },
      {
        "variant": "S",
        "startIndex": 6,
        "isDisplayed": true,
        "parsedForm": "所",
        "vocabId": "30c2ab82-bac4-493f-bed6-85ea24bae3a2"
      },
      {
        "variant": "S",
        "startIndex": 8,
        "isDisplayed": true,
        "parsedForm": "そして",
        "vocabId": "fbb805f8-7e0b-401b-ae1c-df5498d35de1"
      },
      {
        "variant": "B",
        "startIndex": 11,
        "isDisplayed": true,
        "parsedForm": "破壊する",
        "vocabId": "98f1cc21-05a9-4dc3-a38b-28a9fb4f58f5"
      },
      {
        "variant": "S",
        "startIndex": 11,
        "isDisplayed": false,
        "parsedForm": "破壊",
        "vocabId": "4a214190-fe6d-4c26-a14d-2ba559effb10"
      },
      {
        "variant": "S",
        "startIndex": 13,
        "isDisplayed": false,
        "parsedForm": "される",
        "vocabId": "3897ccf9-0454-4a4e-89bf-93414efa1db9"
      },
      {
        "variant": "B",
        "startIndex": 13,
        "isDisplayed": false,
        "parsedForm": "される",
        "vocabId": "3897ccf9-0454-4a4e-89bf-93414efa1db9"
      },
      {
        "variant": "B",
        "startIndex": 13,
        "isDisplayed": false,
        "parsedForm": "する",
        "vocabId": "2ae61cd0-5be8-4599-b48d-a78f97423ddb"
      },
      {
        "variant": "S",
        "startIndex": 13,
        "isDisplayed": true,
        "parsedForm": "あれる",
        "vocabId": "de54cf82-4edc-4afa-9996-189f8a4811f0"
      },
      {
        "variant": "B",
        "startIndex": 13,
        "isDisplayed": false,
        "parsedForm": "あれる",
        "vocabId": "de54cf82-4edc-4afa-9996-189f8a4811f0"
      },
      {
        "variant": "S",
        "startIndex": 15,
        "isDisplayed": true,
        "parsedForm": "うと",
        "vocabId": "4efad35c-59e7-4cfc-b493-1c9d1bd9279c"
      },
      {
        "variant": "S",
        "startIndex": 15,
        "isDisplayed": false,
        "parsedForm": "う",
        "vocabId": "dcca0586-d8a4-4281-9f5f-a50f58a75fb2"
      },
      {
        "variant": "S",
        "startIndex": 16,
        "isDisplayed": false,
        "parsedForm": "と",
        "vocabId": "56979285-581f-4cba-b839-889bc5ce98aa"
      },
      {
        "variant": "S",
        "startIndex": 17,
        "isDisplayed": true,
        "parsedForm": "復旧",
        "vocabId": "4994b98e-f433-4614-8ddc-87f6d963f963"
      },
      {
        "variant": "S",
        "startIndex": 19,
        "isDisplayed": true,
        "parsedForm": "が",
        "vocabId": "2abe98f2-ebd9-4aae-9562-451647960317"
      },
      {
        "variant": "S",
        "startIndex": 20,
        "isDisplayed": true,
        "parsedForm": "難しい",
        "vocabId": "4728aa36-16cc-4fbb-8db5-31080eca32dc"
      },
      {
        "variant": "S",
        "startIndex": 23,
        "isDisplayed": true,
        "parsedForm": "所",
        "vocabId": "30c2ab82-bac4-493f-bed6-85ea24bae3a2"
      }
    ]
  },
  "janomeTokens": "名詞,一般,*,*​速度​速度​*​*​ソクド​ソクド​SYS_DICT\n助詞,格助詞,一般,*​が​が​*​*​ガ​ガ​SYS_DICT\n動詞,自立,*,*​落ちる​落ちる​一段​基本形​オチル​オチル​SYS_DICT\n名詞,非自立,副詞可能,*​所​所​*​*​トコロ​トコロ​SYS_DICT\n記号,空白,*,*​\u3000​\u3000​*​*​\u3000​​SYS_DICT\n接続詞,*,*,*​そして​そして​*​*​ソシテ​ソシテ​SYS_DICT\n名詞,サ変接続,*,*​破壊​破壊​*​*​ハカイ​ハカイ​SYS_DICT\n動詞,自立,*,*​する​さ​サ変・スル​未然レル接続​サ​サ​SYS_DICT\n動詞,接尾,*,*​れる​れる​一段​基本形​レル​レル​SYS_DICT\n助詞,格助詞,引用,*​と​と​*​*​ト​ト​SYS_DICT\n名詞,サ変接続,*,*​復旧​復旧​*​*​フッキュウ​フッキュー​SYS_DICT\n助詞,格助詞,一般,*​が​が​*​*​ガ​ガ​SYS_DICT\n形容詞,自立,*,*​難しい​難しい​形容詞・イ段​基本形​ムズカシイ​ムズカシイ​SYS_DICT\n名詞,非自立,副詞可能,*​所​所​*​*​トコロ​トコロ​SYS_DICT",
  "tags": [
    "-::priority::high::011_Violet_Evergarden",
    "-::sentence::difficulty::6",
    "source::anime::violet::12"
  ]
}