{
  "id": "0efdeb03-ad58-4b4a-a6ce-1312df864e43",
  "sourceQuestion": "ほう ではこの三篠がお手伝いしましょう",
  "userQuestion": "",
  "activeQuestion": "ほう ではこの三篠がお手伝いしましょう",
  "sourceAnswer": "Oh, then I, Misuzu, shall help you.",
  "userAnswer": "",
  "activeAnswer": "Oh, then I, Misuzu, shall help you.",
  "sourceComments": "",
  "userComments": "",
  "reading": "ほうではこの三 篠[しの]がお 手伝[てつだ]いしましょう",
  "externalId": "ny1-nodup_03_0.15.51.590-0.15.55.690",
  "audio": "[sound:ny1-nodup_03_0.15.51.590-0.15.55.690.mp3]",
  "screenshot": "<img src=\"ny1-nodup_03_0.15.53.640.jpg\">",
  "configuration": {
    "highlightedWords": [
      "ましょう",
      "手伝い",
      "三篠",
      "ほう:s.start"
    ],
    "incorrectMatches": [],
    "hiddenMatches": []
  },
  "parsingResult": {
    "sentence": "ほう ではこの三篠がお手伝いしましょう",
    "parserVersion": "text_analysis_0.1",
    "parsedWords": [
      {
        "variant": "S",
        "startIndex": 0,
        "isDisplayed": true,
        "parsedForm": "ほう",
        "vocabId": null
      },
      {
        "variant": "S",
        "startIndex": 3,
        "isDisplayed": true,
        "parsedForm": "では",
        "vocabId": null
      },
      {
        "variant": "S",
        "startIndex": 5,
        "isDisplayed": true,
        "parsedForm": "この",
        "vocabId": null
      },
      {
        "variant": "S",
        "startIndex": 7,
        "isDisplayed": true,
        "parsedForm": "三篠",
        "vocabId": null
      },
      {
        "variant": "S",
        "startIndex": 7,
        "isDisplayed": false,
        "parsedForm": "三",
        "vocabId": null
      },
      {
        "variant": "S",
        "startIndex": 8,
        "isDisplayed": false,
        "parsedForm": "篠",
        "vocabId": null
      },
      {
        "variant": "S",
        "startIndex": 9,
        "isDisplayed": true,
        "parsedForm": "が",
        "vocabId": null
      },
      {
        "variant": "S",
        "startIndex": 10,
        "isDisplayed": true,
        "parsedForm": "お手伝い",
        "vocabId": null
      },
      {
        "variant": "B",
        "startIndex": 14,
        "isDisplayed": true,
        "parsedForm": "します",
        "vocabId": null
      },
      {
        "variant": "B",
        "startIndex": 14,
        "isDisplayed": false,
        "parsedForm": "する",
        "vocabId": null
      },
      {
        "variant": "S",
        "startIndex": 15,
        "isDisplayed": false,
        "parsedForm": "ましょう",
        "vocabId": null
      },
      {
        "variant": "S",
        "startIndex": 15,
        "isDisplayed": false,
        "parsedForm": "ましょ",
        "vocabId": null
      },
      {
        "variant": "B",
        "startIndex": 15,
        "isDisplayed": false,
        "parsedForm": "ます",
        "vocabId": null
      }
    ]
  },
  "janomeTokens": "",
  "tags": [
    "-::priority::high::011_Natsume_01",
    "-::sentence::difficulty::4",
    "legacy_scheduling",
    "source::anime::natsume::s1::03"
  ]
}