{
  "sourceQuestion": "なんかいわくありげって感じだけど",
  "userQuestion": "",
  "activeQuestion": "なんかいわくありげって感じだけど",
  "sourceAnswer": "It seems to have some kind of history.",
  "userAnswer": "",
  "activeAnswer": "It seems to have some kind of history.",
  "sourceComments": "",
  "userComments": "",
  "reading": "なんかいわくありげって 感[かん]じだけど",
  "externalId": "ny1-nodup_05_0.03.53.670-0.03.56.380",
  "audio": "[sound:ny1-nodup_05_0.03.53.670-0.03.56.380.mp3]",
  "screenshot": "<img src=\"ny1-nodup_05_0.03.55.025.jpg\">",
  "configuration": {
    "highlightedWords": [],
    "incorrectMatches": [],
    "hiddenMatches": []
  },
  "parsingResult": {
    "sentence": "なんかいわくありげって感じだけど",
    "parserVersion": "text_analysis_0.1",
    "parsedWords": [
      {
        "variant": "S",
        "startIndex": 0,
        "isDisplayed": true,
        "parsedForm": "なんか",
        "vocabId": "fd6cead6-b645-40d9-b64c-b67e028e3e6d"
      },
      {
        "variant": "S",
        "startIndex": 3,
        "isDisplayed": true,
        "parsedForm": "いわくありげ",
        "vocabId": "a66df689-761b-4504-afa4-a2d73a9c754e"
      },
      {
        "variant": "S",
        "startIndex": 3,
        "isDisplayed": false,
        "parsedForm": "いわく",
        "vocabId": "b288d04b-f564-4277-b964-80accb28befe"
      },
      {
        "variant": "S",
        "startIndex": 6,
        "isDisplayed": false,
        "parsedForm": "ありげ",
        "vocabId": "e96d9cdf-2755-4ceb-a556-bafc547ea73d"
      },
      {
        "variant": "S",
        "startIndex": 6,
        "isDisplayed": false,
        "parsedForm": "あり",
        "vocabId": "4ff7814e-b60a-43f7-b0ef-a0f44ec4f264"
      },
      {
        "variant": "B",
        "startIndex": 6,
        "isDisplayed": false,
        "parsedForm": "ある",
        "vocabId": "a7419593-1381-45c8-88fe-0eb846286151"
      },
      {
        "variant": "S",
        "startIndex": 8,
        "isDisplayed": false,
        "parsedForm": "げ",
        "vocabId": "2fa62937-6a4b-498a-aa48-85ed92436513"
      },
      {
        "variant": "S",
        "startIndex": 9,
        "isDisplayed": true,
        "parsedForm": "って感じ",
        "vocabId": "83ad01bf-92fb-4c32-8f20-3db0ecd1b54f"
      },
      {
        "variant": "S",
        "startIndex": 9,
        "isDisplayed": false,
        "parsedForm": "って",
        "vocabId": "e7744e50-5174-4bca-afc7-6ad527634ad9"
      },
      {
        "variant": "S",
        "startIndex": 11,
        "isDisplayed": false,
        "parsedForm": "感じ",
        "vocabId": "d3207fd9-561e-4c56-a097-d8d432aec063"
      },
      {
        "variant": "S",
        "startIndex": 13,
        "isDisplayed": true,
        "parsedForm": "だけど",
        "vocabId": "efb594c0-b6dd-46a0-9a3b-265e53b1cfdc"
      },
      {
        "variant": "S",
        "startIndex": 13,
        "isDisplayed": false,
        "parsedForm": "だ",
        "vocabId": "32d275aa-5811-482d-b2f3-7e6d2080ac53"
      },
      {
        "variant": "S",
        "startIndex": 14,
        "isDisplayed": false,
        "parsedForm": "けど",
        "vocabId": "fd306f09-1bc3-4f74-ab92-95e10af2db51"
      }
    ]
  },
  "janomeTokens": "フィラー,*,*,*​なんか​なんか​*​*​ナンカ​ナンカ​SYS_DICT\n名詞,引用文字列,*,*​いわく​いわく​*​*​イワク​イワク​SYS_DICT\n動詞,自立,*,*​ある​あり​五段・ラ行​連用形​アリ​アリ​SYS_DICT\n名詞,接尾,一般,*​げ​げ​*​*​ゲ​ゲ​SYS_DICT\n助詞,格助詞,連語,*​って​って​*​*​ッテ​ッテ​SYS_DICT\n名詞,一般,*,*​感じ​感じ​*​*​カンジ​カンジ​SYS_DICT\n助動詞,*,*,*​だ​だ​特殊・ダ​基本形​ダ​ダ​SYS_DICT\n助詞,接続助詞,*,*​けど​けど​*​*​ケド​ケド​SYS_DICT",
  "id": "acd623d3-907e-4dd5-a165-06a791d162e0",
  "tags": [
    "-::priority::high::011_Natsume_01",
    "-::sentence::difficulty::3",
    "source::anime::natsume::s1::05"
  ]
}