{
  "id": "d511ae59-eea5-4521-a144-0c3cf3225657",
  "sourceQuestion": "おやおや ご親切に",
  "userQuestion": "",
  "activeQuestion": "おやおや ご親切に",
  "sourceAnswer": "Oh my, you're so kind.",
  "userAnswer": "",
  "activeAnswer": "Oh my, you're so kind.",
  "sourceComments": "",
  "userComments": "",
  "reading": "おやおやご 親切[しんせつ]に",
  "externalId": "ny3-nodup_01_0.08.19.220-0.08.21.320",
  "audio": "[sound:ny3-nodup_01_0.08.19.220-0.08.21.320.mp3]",
  "screenshot": "<img src=\"ny3-nodup_01_0.08.20.310.jpg\">",
  "configuration": {
    "highlightedWords": [],
    "incorrectMatches": [],
    "hiddenMatches": []
  },
  "parsingResult": {
    "sentence": "おやおや ご親切に",
    "parserVersion": "text_analysis_0.1",
    "parsedWords": [
      {
        "variant": "S",
        "startIndex": 0,
        "isDisplayed": true,
        "parsedForm": "おやおや",
        "vocabId": "94175c5e-8823-47fe-b00e-9849802fd8c4"
      },
      {
        "variant": "S",
        "startIndex": 0,
        "isDisplayed": false,
        "parsedForm": "おや",
        "vocabId": "ba6219ca-ffff-490e-b035-b12d0c8cce43"
      },
      {
        "variant": "S",
        "startIndex": 2,
        "isDisplayed": false,
        "parsedForm": "おや",
        "vocabId": "ba6219ca-ffff-490e-b035-b12d0c8cce43"
      },
      {
        "variant": "S",
        "startIndex": 5,
        "isDisplayed": true,
        "parsedForm": "ご親切に",
        "vocabId": "64c35243-bff7-4631-a5a2-f0fa4c6b5416"
      },
      {
        "variant": "S",
        "startIndex": 5,
        "isDisplayed": false,
        "parsedForm": "ご",
        "vocabId": "1ea14bdd-cc30-44ea-b8da-cdcc3a2e612b"
      },
      {
        "variant": "S",
        "startIndex": 6,
        "isDisplayed": false,
        "parsedForm": "親切に",
        "vocabId": "8e04422f-1489-41fd-9c70-7084cc129261"
      },
      {
        "variant": "S",
        "startIndex": 6,
        "isDisplayed": false,
        "parsedForm": "親切",
        "vocabId": "95aba18d-6d1c-4e88-a691-1117d29b3ff5"
      },
      {
        "variant": "S",
        "startIndex": 8,
        "isDisplayed": false,
        "parsedForm": "に",
        "vocabId": "7391aab7-d24e-4260-8395-e7b757406ef6"
      }
    ]
  },
  "janomeTokens": "感動詞,*,*,*​おや​おや​*​*​オヤ​オヤ​SYS_DICT\n感動詞,*,*,*​おや​おや​*​*​オヤ​オヤ​SYS_DICT\n記号,空白,*,*​ ​ ​*​*​*​*​UNKNOWN\n接頭詞,名詞接続,*,*​ご​ご​*​*​ゴ​ゴ​SYS_DICT\n名詞,形容動詞語幹,*,*​親切​親切​*​*​シンセツ​シンセツ​SYS_DICT\n助詞,副詞化,*,*​に​に​*​*​ニ​ニ​SYS_DICT",
  "tags": [
    "-::priority::high::011_Natsume_03",
    "-::sentence::difficulty::2",
    "source::anime::natsume::s3::01"
  ]
}