{
  "id": "ade9760e-df58-4b6f-821a-827ea7a95e4f",
  "sourceQuestion": "けれど その日から虹を見るたび 三色じゃありませんねって残念そうに言うんだ",
  "userQuestion": "",
  "activeQuestion": "けれど その日から虹を見るたび 三色じゃありませんねって残念そうに言うんだ",
  "sourceAnswer": "But ever since that day, whenever she saw a rainbow, she would say that it wasn't a three-colored one, as if disappointed.",
  "userAnswer": "",
  "activeAnswer": "But ever since that day, whenever she saw a rainbow, she would say that it wasn't a three-colored one, as if disappointed.",
  "sourceComments": "",
  "userComments": "",
  "reading": "けれどその 日[ひ]から 虹[にじ]を 見[み]るたび三 色[しょく]じゃありませんねって 残念[ざんねん]そうに 言[い]うんだ",
  "externalId": "ny2-nodup_02_0.10.24.820-0.10.30.260",
  "audio": "[sound:ny2-nodup_02_0.10.24.820-0.10.30.260.mp3]",
  "screenshot": "<img src=\"ny2-nodup_02_0.10.27.540.jpg\">",
  "configuration": {
    "highlightedWords": [],
    "incorrectMatches": [],
    "hiddenMatches": []
  },
  "parsingResult": {
    "sentence": "けれど その日から虹を見るたび 三色じゃありませんねって残念そうに言うんだ",
    "parserVersion": "text_analysis_0.1",
    "parsedWords": [
      {
        "variant": "S",
        "startIndex": 0,
        "isDisplayed": true,
        "parsedForm": "けれど",
        "vocabId": "ee1bcf84-6d07-452d-abe7-a3c7c964cdfb"
      },
      {
        "variant": "S",
        "startIndex": 4,
        "isDisplayed": true,
        "parsedForm": "その日",
        "vocabId": "233d0996-6235-4fc0-898d-f706b08d6a0c"
      },
      {
        "variant": "S",
        "startIndex": 4,
        "isDisplayed": false,
        "parsedForm": "その",
        "vocabId": "6ac914bd-15bc-475c-8038-59146a91e948"
      },
      {
        "variant": "S",
        "startIndex": 6,
        "isDisplayed": false,
        "parsedForm": "日",
        "vocabId": "33f10003-e27e-4fb7-841d-88e0980316ec"
      },
      {
        "variant": "S",
        "startIndex": 7,
        "isDisplayed": true,
        "parsedForm": "から",
        "vocabId": "77e1176a-5b4a-446a-b814-35a53ab5fb71"
      },
      {
        "variant": "S",
        "startIndex": 9,
        "isDisplayed": true,
        "parsedForm": "虹",
        "vocabId": "eee036cf-a35b-445c-a923-c9e488169185"
      },
      {
        "variant": "S",
        "startIndex": 10,
        "isDisplayed": true,
        "parsedForm": "を",
        "vocabId": "0b5bd909-4c0e-4f1c-bde3-c91719eb579a"
      },
      {
        "variant": "S",
        "startIndex": 11,
        "isDisplayed": true,
        "parsedForm": "見る",
        "vocabId": "147ddbba-0101-430a-9e08-14c59f158c8b"
      },
      {
        "variant": "B",
        "startIndex": 11,
        "isDisplayed": false,
        "parsedForm": "見る",
        "vocabId": "147ddbba-0101-430a-9e08-14c59f158c8b"
      },
      {
        "variant": "S",
        "startIndex": 12,
        "isDisplayed": true,
        "parsedForm": "う",
        "vocabId": "dcca0586-d8a4-4281-9f5f-a50f58a75fb2"
      },
      {
        "variant": "S",
        "startIndex": 13,
        "isDisplayed": true,
        "parsedForm": "たび",
        "vocabId": "e3b3b92e-9a9b-4339-8132-dc664ebb5f6a"
      },
      {
        "variant": "S",
        "startIndex": 16,
        "isDisplayed": true,
        "parsedForm": "三色",
        "vocabId": "2f5fceec-9ca2-4fa6-8a1d-4da764a9460b"
      },
      {
        "variant": "S",
        "startIndex": 16,
        "isDisplayed": false,
        "parsedForm": "三",
        "vocabId": null
      },
      {
        "variant": "S",
        "startIndex": 17,
        "isDisplayed": false,
        "parsedForm": "色",
        "vocabId": "96d95e08-d294-4ba0-bd63-8a2606ae6473"
      },
      {
        "variant": "S",
        "startIndex": 18,
        "isDisplayed": true,
        "parsedForm": "じゃありません",
        "vocabId": "0fb5d67d-0653-431f-bade-809b65df82db"
      },
      {
        "variant": "S",
        "startIndex": 18,
        "isDisplayed": false,
        "parsedForm": "じゃ",
        "vocabId": "4b6b767c-3a51-4bf8-9ed4-16ccb837b355"
      },
      {
        "variant": "S",
        "startIndex": 20,
        "isDisplayed": false,
        "parsedForm": "ありません",
        "vocabId": "b730d306-9fb4-44e0-87c8-a2644d297a06"
      },
      {
        "variant": "B",
        "startIndex": 20,
        "isDisplayed": false,
        "parsedForm": "あります",
        "vocabId": "7eccbea0-50cf-4d05-be38-19d53501bf0d"
      },
      {
        "variant": "S",
        "startIndex": 20,
        "isDisplayed": false,
        "parsedForm": "あり",
        "vocabId": "4ff7814e-b60a-43f7-b0ef-a0f44ec4f264"
      },
      {
        "variant": "B",
        "startIndex": 20,
        "isDisplayed": false,
        "parsedForm": "ある",
        "vocabId": "a7419593-1381-45c8-88fe-0eb846286151"
      },
      {
        "variant": "S",
        "startIndex": 22,
        "isDisplayed": false,
        "parsedForm": "ません",
        "vocabId": "87a1d61e-2ec6-4d98-9b75-1ff2ca9a7bd0"
      },
      {
        "variant": "B",
        "startIndex": 22,
        "isDisplayed": false,
        "parsedForm": "ます",
        "vocabId": "d3765dc0-d7b5-439a-81ab-84ba2f89b7b7"
      },
      {
        "variant": "S",
        "startIndex": 24,
        "isDisplayed": false,
        "parsedForm": "ん",
        "vocabId": "cc6433c2-80a1-498d-8f0d-9da2a46c2885"
      },
      {
        "variant": "S",
        "startIndex": 25,
        "isDisplayed": true,
        "parsedForm": "ね",
        "vocabId": "b85b71b0-b473-4af5-bfa2-f0d824577845"
      },
      {
        "variant": "S",
        "startIndex": 26,
        "isDisplayed": true,
        "parsedForm": "って",
        "vocabId": "e7744e50-5174-4bca-afc7-6ad527634ad9"
      },
      {
        "variant": "S",
        "startIndex": 28,
        "isDisplayed": true,
        "parsedForm": "残念",
        "vocabId": "1baa93f9-5249-4dce-9b68-e78f38fceaa1"
      },
      {
        "variant": "S",
        "startIndex": 30,
        "isDisplayed": true,
        "parsedForm": "そうに",
        "vocabId": "82e7a41f-47e8-4546-997e-33901aa2d2dc"
      },
      {
        "variant": "S",
        "startIndex": 30,
        "isDisplayed": false,
        "parsedForm": "そう",
        "vocabId": "44716e6f-ab3a-4065-bb8f-0ef3ca5b05a3"
      },
      {
        "variant": "S",
        "startIndex": 32,
        "isDisplayed": false,
        "parsedForm": "に",
        "vocabId": "7391aab7-d24e-4260-8395-e7b757406ef6"
      },
      {
        "variant": "S",
        "startIndex": 33,
        "isDisplayed": true,
        "parsedForm": "言う",
        "vocabId": "b7cefd46-499a-4c9c-9f06-3eed04e1d410"
      },
      {
        "variant": "B",
        "startIndex": 33,
        "isDisplayed": false,
        "parsedForm": "言う",
        "vocabId": "b7cefd46-499a-4c9c-9f06-3eed04e1d410"
      },
      {
        "variant": "S",
        "startIndex": 35,
        "isDisplayed": true,
        "parsedForm": "んだ",
        "vocabId": "83865919-ae21-4d86-b814-f700651c09ac"
      },
      {
        "variant": "S",
        "startIndex": 35,
        "isDisplayed": false,
        "parsedForm": "ん",
        "vocabId": "cc6433c2-80a1-498d-8f0d-9da2a46c2885"
      },
      {
        "variant": "S",
        "startIndex": 36,
        "isDisplayed": false,
        "parsedForm": "だ",
        "vocabId": "32d275aa-5811-482d-b2f3-7e6d2080ac53"
      }
    ]
  },
  "janomeTokens": "接続詞,*,*,*​けれど​けれど​*​*​ケレド​ケレド​SYS_DICT\n記号,空白,*,*​ ​ ​*​*​*​*​UNKNOWN\n連体詞,*,*,*​その​その​*​*​ソノ​ソノ​SYS_DICT\n名詞,非自立,副詞可能,*​日​日​*​*​ヒ​ヒ​SYS_DICT\n助詞,格助詞,一般,*​から​から​*​*​カラ​カラ​SYS_DICT\n名詞,一般,*,*​虹​虹​*​*​ニジ​ニジ​SYS_DICT\n助詞,格助詞,一般,*​を​を​*​*​ヲ​ヲ​SYS_DICT\n動詞,自立,*,*​見る​見る​一段​基本形​ミル​ミル​SYS_DICT\n名詞,非自立,副詞可能,*​たび​たび​*​*​タビ​タビ​SYS_DICT\n記号,空白,*,*​ ​ ​*​*​*​*​UNKNOWN\n名詞,数,*,*​三​三​*​*​サン​サン​SYS_DICT\n名詞,接尾,助数詞,*​色​色​*​*​ショク​ショク​SYS_DICT\n助詞,副助詞,*,*​じゃ​じゃ​*​*​ジャ​ジャ​SYS_DICT\n助動詞,*,*,*​ある​あり​五段・ラ行アル​連用形​アリ​アリ​SYS_DICT\n助動詞,*,*,*​ます​ませ​特殊・マス​未然形​マセ​マセ​SYS_DICT\n助動詞,*,*,*​ん​ん​不変化型​基本形​ン​ン​SYS_DICT\n助詞,終助詞,*,*​ね​ね​*​*​ネ​ネ​SYS_DICT\n助詞,格助詞,連語,*​って​って​*​*​ッテ​ッテ​SYS_DICT\n名詞,形容動詞語幹,*,*​残念​残念​*​*​ザンネン​ザンネン​SYS_DICT\n名詞,接尾,助動詞語幹,*​そう​そう​*​*​ソウ​ソー​SYS_DICT\n助詞,副詞化,*,*​に​に​*​*​ニ​ニ​SYS_DICT\n動詞,自立,*,*​言う​言う​五段・ワ行促音便​基本形​イウ​イウ​SYS_DICT\n名詞,非自立,一般,*​ん​ん​*​*​ン​ン​SYS_DICT\n助動詞,*,*,*​だ​だ​特殊・ダ​基本形​ダ​ダ​SYS_DICT",
  "tags": [
    "-::priority::high::011_Natsume_02",
    "-::sentence::difficulty::6",
    "source::anime::natsume::s2::02"
  ]
}