{
  "id": "8ccf1d36-baa5-46dd-93fd-df66a3eacaa7",
  "sourceQuestion": "その言葉 信じてよかろうな",
  "userQuestion": "",
  "activeQuestion": "その言葉 信じてよかろうな",
  "sourceAnswer": "I trust that I can believe in you?",
  "userAnswer": "",
  "activeAnswer": "I trust that I can believe in you?",
  "sourceComments": "",
  "userComments": "",
  "reading": "その 言葉[ことば] 信[しん]じてよかろうな",
  "externalId": "ny2-nodup_04_0.07.09.540-0.07.12.120",
  "audio": "[sound:ny2-nodup_04_0.07.09.540-0.07.12.120.mp3]",
  "screenshot": "<img src=\"ny2-nodup_04_0.07.10.830.jpg\">",
  "configuration": {
    "highlightedWords": [],
    "incorrectMatches": [],
    "hiddenMatches": []
  },
  "parsingResult": {
    "sentence": "その言葉 信じてよかろうな",
    "parserVersion": "text_analysis_0.1",
    "parsedWords": [
      {
        "variant": "S",
        "startIndex": 0,
        "isDisplayed": true,
        "parsedForm": "その",
        "vocabId": null
      },
      {
        "variant": "S",
        "startIndex": 2,
        "isDisplayed": true,
        "parsedForm": "言葉",
        "vocabId": null
      },
      {
        "variant": "B",
        "startIndex": 5,
        "isDisplayed": true,
        "parsedForm": "信じる",
        "vocabId": null
      },
      {
        "variant": "S",
        "startIndex": 7,
        "isDisplayed": true,
        "parsedForm": "て",
        "vocabId": null
      },
      {
        "variant": "S",
        "startIndex": 8,
        "isDisplayed": true,
        "parsedForm": "よかろう",
        "vocabId": null
      },
      {
        "variant": "B",
        "startIndex": 8,
        "isDisplayed": false,
        "parsedForm": "よい",
        "vocabId": null
      },
      {
        "variant": "S",
        "startIndex": 10,
        "isDisplayed": false,
        "parsedForm": "おう",
        "vocabId": null
      },
      {
        "variant": "S",
        "startIndex": 12,
        "isDisplayed": true,
        "parsedForm": "な",
        "vocabId": null
      }
    ]
  },
  "janomeTokens": "",
  "tags": [
    "-::priority::high::011_Natsume_02",
    "-::sentence::difficulty::3",
    "source::anime::natsume::s2::04"
  ]
}