{
  "id": "5e9c65f9-1e5a-43e9-9353-baf60b8d57b5",
  "sourceQuestion": "妹はとても<b>おしゃべり</b>です。",
  "userQuestion": "",
  "activeQuestion": "妹はとてもおしゃべりです。",
  "sourceAnswer": "My little sister's very talkative.",
  "userAnswer": "",
  "activeAnswer": "My little sister's very talkative.",
  "sourceComments": "",
  "userComments": "",
  "reading": "いもうと は とても <b>おしゃべり</b> です",
  "externalId": "sentence:249659",
  "audio": "[sound:746fb34627b73ca61fe7997fffe431e1.mp3]",
  "screenshot": "<img src=\"548aba45c391ab862cc6089d3d1aec14.jpg\">",
  "configuration": {
    "highlightedWords": [
      "おしゃべり"
    ],
    "incorrectMatches": [],
    "hiddenMatches": []
  },
  "parsingResult": {
    "sentence": "妹はとてもおしゃべりです。",
    "parserVersion": "text_analysis_0.1",
    "parsedWords": [
      {
        "variant": "S",
        "startIndex": 0,
        "isDisplayed": true,
        "parsedForm": "妹",
        "vocabId": "d1b67755-e134-4e1f-a091-476690ce9b6d"
      },
      {
        "variant": "S",
        "startIndex": 1,
        "isDisplayed": true,
        "parsedForm": "は",
        "vocabId": "825f4f56-9e9b-4eb9-92e2-099dc6d0c677"
      },
      {
        "variant": "S",
        "startIndex": 2,
        "isDisplayed": true,
        "parsedForm": "とても",
        "vocabId": "6291ebd5-38f8-491b-b04a-f9c92e3cc63a"
      },
      {
        "variant": "S",
        "startIndex": 5,
        "isDisplayed": true,
        "parsedForm": "おしゃべり",
        "vocabId": "afe6879f-3576-45ee-ae52-ae0555853ecd"
      },
      {
        "variant": "S",
        "startIndex": 10,
        "isDisplayed": true,
        "parsedForm": "です",
        "vocabId": "01fd4128-aa4d-4a4d-a529-1e7a3b5d4a0a"
      }
    ]
  },
  "janomeTokens": "名詞,一般,*,*​妹​妹​*​*​イモウト​イモート​SYS_DICT\n助詞,係助詞,*,*​は​は​*​*​ハ​ワ​SYS_DICT\n副詞,助詞類接続,*,*​とても​とても​*​*​トテモ​トテモ​SYS_DICT\n名詞,サ変接続,*,*​おしゃべり​おしゃべり​*​*​オシャベリ​オシャベリ​SYS_DICT\n助動詞,*,*,*​です​です​特殊・デス​基本形​デス​デス​SYS_DICT\n記号,句点,*,*​。​。​*​*​。​。​SYS_DICT",
  "tags": [
    "-::priority::low::110_core_2000",
    "-::sentence::difficulty::3",
    "source::core2000::step07"
  ]
}