{
  "sourceQuestion": "全てのカルトには、何らかの共通の特質があるような気がします。",
  "userQuestion": "",
  "activeQuestion": "全てのカルトには、何らかの共通の特質があるような気がします。",
  "sourceAnswer": "I feel like all cults have some common traits.",
  "userAnswer": "",
  "activeAnswer": "I feel like all cults have some common traits.",
  "sourceComments": "",
  "userComments": "",
  "reading": "",
  "externalId": "",
  "audio": "[sound:hypertts-fe531519519221b2618e3f7717c8980a68f70ceae7fd32ca6e6cd940.mp3]",
  "screenshot": "",
  "configuration": {
    "highlightedWords": [
      "特質"
    ],
    "incorrectMatches": [],
    "hiddenMatches": []
  },
  "parsingResult": {
    "sentence": "全てのカルトには、何らかの共通の特質があるような気がします。",
    "parserVersion": "text_analysis_0.1",
    "parsedWords": [
      {
        "variant": "S",
        "startIndex": 0,
        "isDisplayed": true,
        "parsedForm": "全て",
        "vocabId": "ebf4b932-6f36-4cfa-ad21-cec22cdccf60"
      },
      {
        "variant": "S",
        "startIndex": 2,
        "isDisplayed": true,
        "parsedForm": "の",
        "vocabId": "33bf9bc1-0744-4973-8d45-5776bc54eac1"
      },
      {
        "variant": "S",
        "startIndex": 3,
        "isDisplayed": true,
        "parsedForm": "カルト",
        "vocabId": "ab634609-2de6-4539-b7a5-4822f012e83c"
      },
      {
        "variant": "S",
        "startIndex": 6,
        "isDisplayed": true,
        "parsedForm": "には",
        "vocabId": "b3826859-6d6f-4587-8246-310ba756b6dd"
      },
      {
        "variant": "S",
        "startIndex": 6,
        "isDisplayed": false,
        "parsedForm": "に",
        "vocabId": "7391aab7-d24e-4260-8395-e7b757406ef6"
      },
      {
        "variant": "S",
        "startIndex": 7,
        "isDisplayed": false,
        "parsedForm": "は",
        "vocabId": "825f4f56-9e9b-4eb9-92e2-099dc6d0c677"
      },
      {
        "variant": "S",
        "startIndex": 9,
        "isDisplayed": true,
        "parsedForm": "何らかの",
        "vocabId": "527c1dd2-4519-4862-b08b-97cbe931179b"
      },
      {
        "variant": "S",
        "startIndex": 13,
        "isDisplayed": true,
        "parsedForm": "共通",
        "vocabId": "1caedeed-85b9-41ae-b60b-21bbb72f63b7"
      },
      {
        "variant": "S",
        "startIndex": 15,
        "isDisplayed": true,
        "parsedForm": "の",
        "vocabId": "33bf9bc1-0744-4973-8d45-5776bc54eac1"
      },
      {
        "variant": "S",
        "startIndex": 16,
        "isDisplayed": true,
        "parsedForm": "特質",
        "vocabId": "590f0583-1455-458f-9359-dd2a33ffca74"
      },
      {
        "variant": "S",
        "startIndex": 18,
        "isDisplayed": true,
        "parsedForm": "がある",
        "vocabId": "6d2ff318-7d70-4d0e-9f14-338b0fa53105"
      },
      {
        "variant": "B",
        "startIndex": 18,
        "isDisplayed": false,
        "parsedForm": "がある",
        "vocabId": "6d2ff318-7d70-4d0e-9f14-338b0fa53105"
      },
      {
        "variant": "S",
        "startIndex": 18,
        "isDisplayed": false,
        "parsedForm": "が",
        "vocabId": "2abe98f2-ebd9-4aae-9562-451647960317"
      },
      {
        "variant": "S",
        "startIndex": 19,
        "isDisplayed": false,
        "parsedForm": "ある",
        "vocabId": "a7419593-1381-45c8-88fe-0eb846286151"
      },
      {
        "variant": "B",
        "startIndex": 19,
        "isDisplayed": false,
        "parsedForm": "ある",
        "vocabId": "a7419593-1381-45c8-88fe-0eb846286151"
      },
      {
        "variant": "B",
        "startIndex": 20,
        "isDisplayed": true,
        "parsedForm": "う",
        "vocabId": "dcca0586-d8a4-4281-9f5f-a50f58a75fb2"
      },
      {
        "variant": "B",
        "startIndex": 21,
        "isDisplayed": true,
        "parsedForm": "ような気がする",
        "vocabId": "586d34a7-309d-4c6e-8a00-bc866b0a1c44"
      },
      {
        "variant": "S",
        "startIndex": 21,
        "isDisplayed": false,
        "parsedForm": "ような",
        "vocabId": "8189a99d-3090-43d7-b390-e7bc058c0f00"
      },
      {
        "variant": "S",
        "startIndex": 21,
        "isDisplayed": false,
        "parsedForm": "よう",
        "vocabId": "a2317963-e961-4c96-bcc4-8ad9ffbb738e"
      },
      {
        "variant": "S",
        "startIndex": 23,
        "isDisplayed": false,
        "parsedForm": "な",
        "vocabId": "89b0d902-b2dd-4f1f-a0dc-4f6565616c64"
      },
      {
        "variant": "B",
        "startIndex": 24,
        "isDisplayed": false,
        "parsedForm": "気がする",
        "vocabId": "c37adeac-5acf-4e7b-b9ef-f491826d3aba"
      },
      {
        "variant": "S",
        "startIndex": 24,
        "isDisplayed": false,
        "parsedForm": "気",
        "vocabId": "da628d09-0c31-4ba3-92bb-f085e5c784a3"
      },
      {
        "variant": "B",
        "startIndex": 25,
        "isDisplayed": false,
        "parsedForm": "がする",
        "vocabId": "fc25db31-fec4-49c4-9dde-23371b90efb2"
      },
      {
        "variant": "S",
        "startIndex": 25,
        "isDisplayed": false,
        "parsedForm": "が",
        "vocabId": "2abe98f2-ebd9-4aae-9562-451647960317"
      },
      {
        "variant": "S",
        "startIndex": 26,
        "isDisplayed": false,
        "parsedForm": "します",
        "vocabId": "8cb6e61d-618a-4175-be52-89f137bc202f"
      },
      {
        "variant": "B",
        "startIndex": 26,
        "isDisplayed": false,
        "parsedForm": "する",
        "vocabId": "2ae61cd0-5be8-4599-b48d-a78f97423ddb"
      },
      {
        "variant": "S",
        "startIndex": 27,
        "isDisplayed": true,
        "parsedForm": "ます",
        "vocabId": "d3765dc0-d7b5-439a-81ab-84ba2f89b7b7"
      }
    ]
  },
  "janomeTokens": "名詞,副詞可能,*,*​全て​全て​*​*​スベテ​スベテ​SYS_DICT\n助詞,連体化,*,*​の​の​*​*​ノ​ノ​SYS_DICT\n名詞,一般,*,*​カルト​カルト​*​*​カルト​カルト​SYS_DICT\n助詞,格助詞,一般,*​に​に​*​*​ニ​ニ​SYS_DICT\n助詞,係助詞,*,*​は​は​*​*​ハ​ワ​SYS_DICT\n記号,読点,*,*​、​、​*​*​、​、​SYS_DICT\n連体詞,*,*,*​何らかの​何らかの​*​*​ナンラカノ​ナンラカノ​SYS_DICT\n名詞,サ変接続,*,*​共通​共通​*​*​キョウツウ​キョーツー​SYS_DICT\n助詞,連体化,*,*​の​の​*​*​ノ​ノ​SYS_DICT\n名詞,一般,*,*​特質​特質​*​*​トクシツ​トクシツ​SYS_DICT\n助詞,格助詞,一般,*​が​が​*​*​ガ​ガ​SYS_DICT\n動詞,自立,*,*​ある​ある​五段・ラ行​基本形​アル​アル​SYS_DICT\n名詞,非自立,助動詞語幹,*​よう​よう​*​*​ヨウ​ヨー​SYS_DICT\n助動詞,*,*,*​だ​な​特殊・ダ​体言接続​ナ​ナ​SYS_DICT\n名詞,非自立,一般,*​気​気​*​*​キ​キ​SYS_DICT\n助詞,格助詞,一般,*​が​が​*​*​ガ​ガ​SYS_DICT\n動詞,自立,*,*​する​し​サ変・スル​連用形​シ​シ​SYS_DICT\n助動詞,*,*,*​ます​ます​特殊・マス​基本形​マス​マス​SYS_DICT\n記号,句点,*,*​。​。​*​*​。​。​SYS_DICT",
  "id": "a6ab86f9-a0d4-484b-a81c-fbacbc6c68f0",
  "tags": [
    "_tts_audio",
    "-::priority::low::120_tts",
    "-::sentence::difficulty::6",
    "source::wani",
    "source::wani::current"
  ]
}