{
  "question": "なんてこった",
  "sourceAnswer": "what-the-hell/oh,-great!/son-of-a-gun/holy-mackerel/oh-no!/holy-cow!/damn!",
  "userAnswer": "",
  "activeAnswer": "what-the-hell/oh,-great!/son-of-a-gun/holy-mackerel/oh-no!/holy-cow!/damn!",
  "userExplanation": "",
  "userExplanationLong": "",
  "userMnemonic": "",
  "userCompounds": [],
  "readings": [
    "なんてこった"
  ],
  "partsOfSpeech": "interjection",
  "sourceMnemonic": "",
  "sourceReadingMnemonic": "",
  "audioB": "",
  "audioG": "",
  "audioTTS": "[sound:hypertts-f2c2f19979ed12e5eb5711fc0754b62db2ac84588da93037dc70e59a.mp3]",
  "forms": [
    "なんてこった"
  ],
  "sentenceCount": 0,
  "matchingRules": {
    "prefixIsNot": [],
    "suffixIsNot": [],
    "surfaceIsNot": [],
    "yieldToSurface": [],
    "requiredPrefix": []
  },
  "relatedVocab": {
    "ergativeTwin": "",
    "derivedFrom": "",
    "perfectSynonyms": [],
    "synonyms": [],
    "antonyms": [],
    "confusedWith": [],
    "seeAlso": []
  },
  "id": "78036075-9ccf-4bc6-b3ca-d6fb2905d30b",
  "tags": [
    "_uk",
    "-::vocab::has-no-studying-sentences",
    "source::jamdict"
  ]
}